{
  "meta": {
    "subject": "География База",
    "subject_cluster": "гуманитарные и социальные",
    "grades": "10-11",
    "level": "базовый",
    "total_hours": 68,
    "hours_per_grade": { "10": 34, "11": 34 },
    "federal_program": "ФРП по географии 10-11 классы, базовый уровень (2022, приказ МП РФ № 858)",
    "base_umk": "Максаковский В.П. / Таможняя Е.А. и др. — География. Базовый уровень 10-11 (Просвещение / Дрофа, в ФПУ)",
    "methodology": "ЖУ360 v5.1",
    "poiya_integration": false,
    "created": "2026-02-28",
    "version": "1.0"
  },
  "sections": [
    {
      "id": "gb10-1",
      "grade": 10,
      "title": "Географическая наука. Современный мир",
      "hours": 4,
      "mode_ratio": "Открытие 70% / Закрепление 30%",
      "key_accent": "Объект и предмет географии, источники географической информации, методы исследования. Картографические проекции, ГИС. Глобализация и её географические проявления.",
      "main_techniques": [
        "Работа с картами и ГИС",
        "Анализ статистических данных",
        "Исследование"
      ]
    },
    {
      "id": "gb10-2",
      "grade": 10,
      "title": "Природа Земли: ресурсы и риски",
      "hours": 8,
      "mode_ratio": "Открытие 55% / Закрепление 45%",
      "key_accent": "Природные ресурсы и их классификация. Ресурсообеспеченность. Экологические проблемы. Природные катастрофы и риски. Рациональное природопользование.",
      "main_techniques": [
        "Анализ карт природных ресурсов",
        "Работа со статистикой",
        "Дискуссия о природопользовании"
      ]
    },
    {
      "id": "gb10-3",
      "grade": 10,
      "title": "Население мира",
      "hours": 10,
      "mode_ratio": "Открытие 60% / Закрепление 40%",
      "key_accent": "Численность и воспроизводство населения. Демографический переход. Половозрастная структура. Миграции. Размещение населения, урбанизация. Этнический и религиозный состав.",
      "main_techniques": [
        "Работа с демографическими пирамидами",
        "Анализ картограмм и карто-диаграмм",
        "Сравнительная характеристика стран"
      ]
    },
    {
      "id": "gb10-4",
      "grade": 10,
      "title": "Мировое хозяйство: общая характеристика",
      "hours": 12,
      "mode_ratio": "Открытие 50% / Закрепление 50%",
      "key_accent": "НТР и её влияние на экономику. Отраслевая структура хозяйства. Промышленность (топливная, электроэнергетика, металлургия, машиностроение, химическая, лёгкая). Сельское хозяйство. Транспорт. МЭО и интеграция.",
      "main_techniques": [
        "Составление экономических характеристик отраслей",
        "Работа с картами хозяйства мира",
        "Практические работы с атласом"
      ]
    },
    {
      "id": "gb11-1",
      "grade": 11,
      "title": "Регионы мира: Зарубежная Европа и СНГ",
      "hours": 8,
      "mode_ratio": "Открытие 60% / Закрепление 40%",
      "key_accent": "ЭГП и природные условия Европы. Население, урбанизация. Структура хозяйства, ведущие страны. СНГ: постсоветское пространство, Россия в региональном контексте.",
      "main_techniques": [
        "Страновые характеристики",
        "Работа с политической и экономической картой",
        "Сравнительный анализ"
      ]
    },
    {
      "id": "gb11-2",
      "grade": 11,
      "title": "Регионы мира: Азия, Африка, Америка, Австралия",
      "hours": 14,
      "mode_ratio": "Открытие 55% / Закрепление 45%",
      "key_accent": "Зарубежная Азия: Японии, Китай, Индия — экономические портреты. Юго-Восточная Азия. Африка — ресурсы, проблемы. Северная и Латинская Америка. Австралия и Океания.",
      "main_techniques": [
        "Характеристика ЭГП по плану",
        "Составление картосхем",
        "Сравнение регионов"
      ]
    },
    {
      "id": "gb11-3",
      "grade": 11,
      "title": "Россия в современном мире",
      "hours": 6,
      "mode_ratio": "Открытие 50% / Закрепление 50%",
      "key_accent": "Место России в мировой экономике и геополитике. Внешнеэкономические связи. Экологические вызовы и устойчивое развитие. Россия и международные организации.",
      "main_techniques": [
        "Работа со статистическими материалами",
        "Дискуссия",
        "Проектная работа"
      ]
    },
    {
      "id": "gb11-4",
      "grade": 11,
      "title": "Глобальные проблемы человечества",
      "hours": 6,
      "mode_ratio": "Открытие 65% / Закрепление 35%",
      "key_accent": "Классификация глобальных проблем. Продовольственная, энергетическая, экологическая, демографическая проблемы. Пути решения. Устойчивое развитие и цели ООН.",
      "main_techniques": [
        "Дискуссия и дебаты",
        "Проектная работа",
        "Исследование и презентация"
      ]
    }
  ]
}
