{
  "meta": {
    "subject": "Обществознание",
    "grades": "10-11",
    "level": "базовый",
    "total_hours": 123,
    "source": "ФРП СОО 2025"
  },
  "sections": [
    {
      "grade": 10,
      "title": "Общество",
      "hours": 3
    },
    {
      "grade": 10,
      "title": "Информационное общество",
      "hours": 2
    },
    {
      "grade": 10,
      "title": "Становление человека и общества",
      "hours": 3
    },
    {
      "grade": 10,
      "title": "Деятельность человека",
      "hours": 2
    },
    {
      "grade": 10,
      "title": "Познавательная деятельность",
      "hours": 3
    },
    {
      "grade": 10,
      "title": "Повторительно-обобщающий урок",
      "hours": 2
    },
    {
      "grade": 10,
      "title": "Культура и её разновидности",
      "hours": 3
    },
    {
      "grade": 10,
      "title": "Категории духовной культуры",
      "hours": 3
    },
    {
      "grade": 10,
      "title": "Наука и образование",
      "hours": 4
    },
    {
      "grade": 10,
      "title": "Религия",
      "hours": 2
    },
    {
      "grade": 10,
      "title": "Искусство",
      "hours": 2
    },
    {
      "grade": 10,
      "title": "Повторительно-обобщающий урок",
      "hours": 2
    },
    {
      "grade": 10,
      "title": "Экономика – основа жизни общества",
      "hours": 6
    },
    {
      "grade": 10,
      "title": "Рыночные отношения",
      "hours": 6
    },
    {
      "grade": 10,
      "title": "Экономическая деятельность",
      "hours": 2
    },
    {
      "grade": 10,
      "title": "Экономика предприятия",
      "hours": 4
    },
    {
      "grade": 10,
      "title": "Финансовый рынок",
      "hours": 3
    },
    {
      "grade": 10,
      "title": "Экономика и государство",
      "hours": 3
    },
    {
      "grade": 10,
      "title": "Мировая экономика",
      "hours": 2
    },
    {
      "grade": 10,
      "title": "Повторительно-обобщающий урок",
      "hours": 2
    },
    {
      "grade": 11,
      "title": "Социальная структура общества",
      "hours": 2
    },
    {
      "grade": 11,
      "title": "Социальное неравенство и мобильность",
      "hours": 2
    },
    {
      "grade": 11,
      "title": "Семья и семейные отношения",
      "hours": 2
    },
    {
      "grade": 11,
      "title": "Этнические группы и межнациональные отношения",
      "hours": 2
    },
    {
      "grade": 11,
      "title": "Социальные нормы",
      "hours": 2
    },
    {
      "grade": 11,
      "title": "Социальный контроль",
      "hours": 2
    },
    {
      "grade": 11,
      "title": "Повторительно-обобщающий урок",
      "hours": 2
    },
    {
      "grade": 11,
      "title": "Политическая власть",
      "hours": 2
    },
    {
      "grade": 11,
      "title": "Политическая система общества",
      "hours": 3
    },
    {
      "grade": 11,
      "title": "Государство",
      "hours": 4
    },
    {
      "grade": 11,
      "title": "Политические режимы",
      "hours": 2
    },
    {
      "grade": 11,
      "title": "Политический процесс",
      "hours": 3
    },
    {
      "grade": 11,
      "title": "Избирательная система",
      "hours": 2
    },
    {
      "grade": 11,
      "title": "Политические элиты",
      "hours": 2
    },
    {
      "grade": 11,
      "title": "Повторительно-обобщающий урок",
      "hours": 2
    },
    {
      "grade": 11,
      "title": "Система права. Правовые нормы",
      "hours": 4
    },
    {
      "grade": 11,
      "title": "Конституционные права и обязанности граждан",
      "hours": 4
    },
    {
      "grade": 11,
      "title": "Правовое государство",
      "hours": 6
    },
    {
      "grade": 11,
      "title": "Правовое регулирование",
      "hours": 8
    },
    {
      "grade": 11,
      "title": "Основные принципы права",
      "hours": 6
    },
    {
      "grade": 11,
      "title": "Повторительно-обобщающий урок",
      "hours": 2
    }
  ]
}